{
	"name": "Mochi Japanese With lowercase",
	"mapping": {

		"ぁ": 64,
		"あ": 123,
		"ぃ": 124,
		"い": 125,
		"ぅ": 126,
		"う": 127,
		"ぇ": 128,
		"え": 129,
		"ぉ": 130,
		"お": 131,

		"か": 132,
		"が": 133,
		"き": 134,
		"ぎ": 135,
		"く": 136,
		"ぐ": 137,
		"け": 138,
		"げ": 139,
		"こ": 140,
		"ご": 141,

		"さ": 142,
		"ざ": 143,
		"し": 144,
		"じ": 145,
		"す": 146,
		"ず": 147,
		"せ": 148,
		"ぜ": 149,
		"そ": 150,
		"ぞ": 151,

		"た": 152,
		"だ": 153,
		"ち": 154,
		"ぢ": 155,
		"っ": 156,
		"つ": 157,
		"づ": 158,
		"て": 159,
		"で": 160,
		"と": 161,
		"ど": 162,

		"な": 163,
		"に": 164,
		"ぬ": 165,
		"ね": 166,
		"の": 167,

		"は": 168,
		"ば": 169,
		"ぱ": 170,
		"ひ": 171,
		"び": 172,
		"ぴ": 173,
		"ふ": 174,
		"ぶ": 175,
		"ぷ": 176,
		"へ": 177,
		"べ": 178,
		"ぺ": 179,
		"ほ": 180,
		"ぼ": 181,
		"ぽ": 182,

		"ま": 183,
		"み": 184,
		"む": 185,
		"め": 186,
		"も": 187,

		"ゃ": 188,
		"や": 189,
		"ゅ": 190,
		"ゆ": 191,
		"ょ": 192,
		"よ": 193,

		"ら": 194,
		"り": 195,
		"る": 196,
		"れ": 197,
		"ろ": 198,

		"わ": 199,
		"を": 200,
		"ん": 201,

		"ァ": 205,
		"ア": 206,
		"ィ": 207,
		"イ": 208,
		"ゥ": 209,
		"ウ": 210,
		"ェ": 211,
		"エ": 212,
		"ォ": 213,
		"オ": 214,

		"カ": 215,
		"ガ": 216,
		"キ": 217,
		"ギ": 218,
		"ク": 219,
		"グ": 220,
		"ケ": 221,
		"ゲ": 222,
		"コ": 223,
		"ゴ": 224,

		"サ": 225,
		"ザ": 226,
		"シ": 227,
		"ジ": 228,
		"ス": 229,
		"ズ": 230,
		"セ": 231,
		"ゼ": 232,
		"ソ": 233,
		"ゾ": 234,

		"タ": 235,
		"ダ": 236,
		"チ": 237,
		"ヂ": 238,
		"ッ": 239,
		"ツ": 240,
		"ヅ": 241,
		"テ": 242,
		"デ": 243,
		"ト": 244,
		"ド": 245,

		"ナ": 246,
		"ニ": 247,
		"ヌ": 248,
		"ネ": 249,
		"ノ": 250,

		"ハ": 251,
		"バ": 252,
		"パ": 253,
		"ヒ": 254,
		"ビ": 255,
		"ピ": 34,
		"フ": 35,
		"ブ": 36,
		"プ": 37,
		"ヘ": 177,
		"ベ": 178,
		"ペ": 179,
		"ホ": 38,
		"ボ": 39,
		"ポ": 40,

		"マ": 41,
		"ミ": 42,
		"ム": 43,
		"メ": 44,
		"モ": 45,

		"ャ": 47,
		"ヤ": 58,
		"ュ": 59,
		"ユ": 60,
		"ョ": 61,
		"ヨ": 62,

		"ラ": 91,
		"リ": 92,
		"ル": 93,
		"レ": 94,
		"ロ": 95,

		"ワ": 202,
		"ヲ": 203,
		"ン": 204,

		"！": 33,
		"・": 46,
		"？": 63,
		"　": 32,
		"ー": 96,
		"－": 96,
		"-": 96,

		"０": 48,
		"１": 49,
		"２": 50,
		"３": 51,
		"４": 52,
		"５": 53,
		"６": 54,
		"７": 55,
		"８": 56,
		"９": 57

	}
}
